[{"id":213,"date":"2015-01-20","meals":[{"name":"Breakfast","dishes":[{"name":"Fruit - Banana 7 to 7-7/8 Inch, 1 Medium","nutrients":[{"Calories":105},{"Carbs":27},{"Sat Fat":0},{"Fiber":3},{"Sodium":1},{"Sugar":14}]}]},{"name":"snack","dishes":[{"name":"Apples - Raw, with skin, 1 medium 2-3/4 dia approx 3 per lb","nutrients":[{"Calories":72},{"Carbs":19},{"Sat Fat":0},{"Fiber":3},{"Sodium":1},{"Sugar":14}]}]},{"name":"dinner","dishes":[{"name":"Tyson - Crispy Chicken  Strips, 3 oz","nutrients":[{"Calories":190},{"Carbs":12},{"Sat Fat":2},{"Fiber":1},{"Sodium":480},{"Sugar":0}]},{"name":"Ore Ida - Onion Tater Tots, 9 pieces 90g","nutrients":[{"Calories":160},{"Carbs":21},{"Sat Fat":2},{"Fiber":2},{"Sodium":410},{"Sugar":1}]}]},{"name":"drinks","dishes":[{"name":"Coffee - Brewed from grounds, 2 cup 8 fl oz","nutrients":[{"Calories":5},{"Carbs":0},{"Sat Fat":0},{"Fiber":0},{"Sodium":9},{"Sugar":0}]},{"name":"Milk - Vitamin D, 1 cups","nutrients":[{"Calories":150},{"Carbs":12},{"Sat Fat":5},{"Fiber":0},{"Sodium":125},{"Sugar":12}]},{"name":"Mountain Dew - 12 oz Can, 1 can","nutrients":[{"Calories":170},{"Carbs":46},{"Sat Fat":0},{"Fiber":0},{"Sodium":65},{"Sugar":46}]}]}],"summary":{"total":[{"Calories":852},{"Carbs":137},{"Sat Fat":9},{"Fiber":9},{"Sodium":1091},{"Sugar":87}],"goal":[{"Calories":1200},{"Carbs":150},{"Sat Fat":13},{"Fiber":25},{"Sodium":2300},{"Sugar":45}]}},{"id":213,"date":"2015-01-28","meals":[{"name":"lunch","dishes":[{"name":"Eggs - Fried whole egg, 2.5 large","nutrients":[{"Calories":231},{"Carbs":1},{"Sat Fat":5},{"Fiber":0},{"Sodium":235},{"Sugar":1}]}]}],"summary":{"total":[{"Calories":231},{"Carbs":1},{"Sat Fat":5},{"Fiber":0},{"Sodium":235},{"Sugar":1}],"goal":[{"Calories":1200},{"Carbs":150},{"Sat Fat":13},{"Fiber":25},{"Sodium":2300},{"Sugar":45}]}}]