[{"id":9202,"date":"2014-12-31","meals":[{"name":"breakfast","dishes":[{"name":"Sugar - Sugar, 4 tsp","nutrients":[{"Calories":60}]},{"name":"Sugar - Sugar, 4 tsp","nutrients":[{"Calories":60}]},{"name":"Coffee-mate Original Powder - Coffee Creamer, 4 tsp","nutrients":[{"Calories":40}]},{"name":"Coffee-mate Original Powder - Coffee Creamer, 4 tsp","nutrients":[{"Calories":40}]},{"name":"Coffee - Brewed from grounds, 2 cup 8 fl oz","nutrients":[{"Calories":5}]},{"name":"Coffee - Brewed from grounds, 2 cup 8 fl oz","nutrients":[{"Calories":5}]}]},{"name":"snack","dishes":[{"name":"Orange - Orange - Large, 1 orange 340 grams","nutrients":[{"Calories":90}]},{"name":"Orange - Orange - Large, 1 orange 340 grams","nutrients":[{"Calories":90}]}]},{"name":"lunch","dishes":[{"name":"Walmart Brand - Gala Apples, 1 Large apple","nutrients":[{"Calories":117}]},{"name":"Walmart Brand - Gala Apples, 1 Large apple","nutrients":[{"Calories":117}]}]}],"summary":{"total":[{"Calories":312}],"goal":[{"Calories":1450}]}},{"id":9202,"date":"2015-01-05","meals":[{"name":"breakfast","dishes":[{"name":"Coffee - Brewed from grounds, 2 cup 8 fl oz","nutrients":[{"Calories":5}]},{"name":"Coffee - Brewed from grounds, 2 cup 8 fl oz","nutrients":[{"Calories":5}]},{"name":"Coffee-mate Original Powder - Coffee Creamer, 4 tsp","nutrients":[{"Calories":40}]},{"name":"Coffee-mate Original Powder - Coffee Creamer, 4 tsp","nutrients":[{"Calories":40}]},{"name":"Sugar - Sugar, 4 tsp","nutrients":[{"Calories":60}]},{"name":"Sugar - Sugar, 4 tsp","nutrients":[{"Calories":60}]}]},{"name":"snack","dishes":[{"name":"Bananas - Raw, 1 medium 7 to 7-7/8 long","nutrients":[{"Calories":105}]},{"name":"Bananas - Raw, 1 medium 7 to 7-7/8 long","nutrients":[{"Calories":105}]}]},{"name":"lunch","dishes":[{"name":"Great Value - 100% Whole Wheat Bread - Roundtop, 2 slice 25g or .9oz","nutrients":[{"Calories":120}]},{"name":"Great Value - 100% Whole Wheat Bread - Roundtop, 2 slice 25g or .9oz","nutrients":[{"Calories":120}]},{"name":"Mayo - Mayo, 1 tbs","nutrients":[{"Calories":90}]},{"name":"Mayo - Mayo, 1 tbs","nutrients":[{"Calories":90}]},{"name":"T - Tomato Slice, 2 slice","nutrients":[{"Calories":10}]},{"name":"T - Tomato Slice, 2 slice","nutrients":[{"Calories":10}]}]},{"name":"snack","dishes":[{"name":"Orange - Orange - Large, 1 orange 340 grams","nutrients":[{"Calories":90}]},{"name":"Orange - Orange - Large, 1 orange 340 grams","nutrients":[{"Calories":90}]},{"name":"Bananas - Raw, 1 medium 7 to 7-7/8 long","nutrients":[{"Calories":105}]},{"name":"Bananas - Raw, 1 medium 7 to 7-7/8 long","nutrients":[{"Calories":105}]}]},{"name":"dinner","dishes":[{"name":"Homemade - Spinach and Ricotta Stuffed Shells, 1/4 of dish","nutrients":[{"Calories":449}]},{"name":"Homemade - Spinach and Ricotta Stuffed Shells, 1/4 of dish","nutrients":[{"Calories":449}]},{"name":"Side Salad - W/ Ranch, 3 Oz","nutrients":[{"Calories":120}]},{"name":"Side Salad - W/ Ranch, 3 Oz","nutrients":[{"Calories":120}]}]}],"summary":{"total":[{"Calories":1194}],"goal":[{"Calories":1450}]}},{"id":9202,"date":"2015-01-06","meals":[{"name":"breakfast","dishes":[{"name":"Great Value - Frozen Whole Strawberries, 0.33 Cup 140g","nutrients":[{"Calories":17}]},{"name":"Great Value - Frozen Whole Strawberries, 0.33 Cup 140g","nutrients":[{"Calories":17}]},{"name":"Bananas - Raw, 0.25 medium 7 to 7-7/8 long","nutrients":[{"Calories":26}]},{"name":"Bananas - Raw, 0.25 medium 7 to 7-7/8 long","nutrients":[{"Calories":26}]},{"name":"Silk - Vanilla Soy Milk, 0.5 cup","nutrients":[{"Calories":50}]},{"name":"Silk - Vanilla Soy Milk, 0.5 cup","nutrients":[{"Calories":50}]}]},{"name":"lunch","dishes":[{"name":"T - Tomato Slice, 2 slice","nutrients":[{"Calories":10}]},{"name":"T - Tomato Slice, 2 slice","nutrients":[{"Calories":10}]},{"name":"Mayo - Mayo, 1 tbs","nutrients":[{"Calories":90}]},{"name":"Mayo - Mayo, 1 tbs","nutrients":[{"Calories":90}]},{"name":"Great Value - 100% Whole Wheat Bread - Roundtop, 2 slice 25g or .9oz","nutrients":[{"Calories":120}]},{"name":"Great Value - 100% Whole Wheat Bread - Roundtop, 2 slice 25g or .9oz","nutrients":[{"Calories":120}]},{"name":"Granny Smith - Apple - Medium, 154 g  1 medium","nutrients":[{"Calories":80}]},{"name":"Granny Smith - Apple - Medium, 154 g  1 medium","nutrients":[{"Calories":80}]}]},{"name":"snack","dishes":[{"name":"Bananas - Raw, 0.5 medium 7 to 7-7/8 long","nutrients":[{"Calories":53}]},{"name":"Bananas - Raw, 0.5 medium 7 to 7-7/8 long","nutrients":[{"Calories":53}]},{"name":"Sensible Solutions - Garden Veggie Straws - Zesty Ranch, 38 straws","nutrients":[{"Calories":130}]},{"name":"Sensible Solutions - Garden Veggie Straws - Zesty Ranch, 38 straws","nutrients":[{"Calories":130}]},{"name":"Great Value - Tropical Dried Fruit Mix, 1/3 cup","nutrients":[{"Calories":120}]},{"name":"Great Value - Tropical Dried Fruit Mix, 1/3 cup","nutrients":[{"Calories":120}]},{"name":"Eggs - Hard Boiled - Large, 2 egg","nutrients":[{"Calories":140}]},{"name":"Eggs - Hard Boiled - Large, 2 egg","nutrients":[{"Calories":140}]},{"name":"Burmans - Real Mayo, 2 Tbsp.","nutrients":[{"Calories":200}]},{"name":"Burmans - Real Mayo, 2 Tbsp.","nutrients":[{"Calories":200}]},{"name":"Burmans Aldi Brand - Yellow Mustard, 1 tsp","nutrients":[{"Calories":0}]},{"name":"Burmans Aldi Brand - Yellow Mustard, 1 tsp","nutrients":[{"Calories":0}]},{"name":"Great Value - 100% Whole Wheat Bread - Roundtop, 4 slice 25g or .9oz","nutrients":[{"Calories":240}]},{"name":"Great Value - 100% Whole Wheat Bread - Roundtop, 4 slice 25g or .9oz","nutrients":[{"Calories":240}]}]}],"summary":{"total":[{"Calories":1276}],"goal":[{"Calories":1450}]}},{"id":9202,"date":"2015-01-07","meals":[{"name":"breakfast","dishes":[{"name":"Sugar - Sugar, 2 tsp","nutrients":[{"Calories":30}]},{"name":"Sugar - Sugar, 2 tsp","nutrients":[{"Calories":30}]},{"name":"Coffee-mate Original Powder - Coffee Creamer, 2 tsp","nutrients":[{"Calories":20}]},{"name":"Coffee-mate Original Powder - Coffee Creamer, 2 tsp","nutrients":[{"Calories":20}]},{"name":"Coffee - Brewed from grounds, 1 cup 8 fl oz","nutrients":[{"Calories":2}]},{"name":"Coffee - Brewed from grounds, 1 cup 8 fl oz","nutrients":[{"Calories":2}]}]},{"name":"lunch","dishes":[{"name":"Great Value - 100% Whole Wheat Bread - Roundtop, 4 slice 25g or .9oz","nutrients":[{"Calories":240}]},{"name":"Great Value - 100% Whole Wheat Bread - Roundtop, 4 slice 25g or .9oz","nutrients":[{"Calories":240}]},{"name":"Mayo - Mayo, 2 tbs","nutrients":[{"Calories":180}]},{"name":"Mayo - Mayo, 2 tbs","nutrients":[{"Calories":180}]},{"name":"T - Tomato Slice, 2 slice","nutrients":[{"Calories":10}]},{"name":"T - Tomato Slice, 2 slice","nutrients":[{"Calories":10}]},{"name":"Fresh - Hard Boiled Egg, 1 Large","nutrients":[{"Calories":80}]},{"name":"Fresh - Hard Boiled Egg, 1 Large","nutrients":[{"Calories":80}]},{"name":"Sensible Portons - Garden Veggie Straws Cheddar Cheese, 1 oz 28g about 38 straws","nutrients":[{"Calories":130}]},{"name":"Sensible Portons - Garden Veggie Straws Cheddar Cheese, 1 oz 28g about 38 straws","nutrients":[{"Calories":130}]}]}],"summary":{"total":[{"Calories":692}],"goal":[{"Calories":1450}]}},{"id":9202,"date":"2015-01-09","meals":[{"name":"breakfast","dishes":[{"name":"Coffee - Brewed from grounds, 1 cup 8 fl oz","nutrients":[{"Calories":2}]},{"name":"Coffee - Brewed from grounds, 1 cup 8 fl oz","nutrients":[{"Calories":2}]},{"name":"Sugar - Sugar, 3 tsp","nutrients":[{"Calories":45}]},{"name":"Sugar - Sugar, 3 tsp","nutrients":[{"Calories":45}]},{"name":"Pet - Ultra Pasteurize Half & Half, 2 TBSP","nutrients":[{"Calories":40}]},{"name":"Pet - Ultra Pasteurize Half & Half, 2 TBSP","nutrients":[{"Calories":40}]},{"name":"Pet - Ultra Pasteurize Half & Half, 1 cups","nutrients":[{"Calories":320}]},{"name":"Pet - Ultra Pasteurize Half & Half, 1 cups","nutrients":[{"Calories":320}]},{"name":"Coffee - Brewed from grounds, 1 cup 8 fl oz","nutrients":[{"Calories":2}]},{"name":"Coffee - Brewed from grounds, 1 cup 8 fl oz","nutrients":[{"Calories":2}]},{"name":"Sugar - Sugar Granulated, 3 tbsps","nutrients":[{"Calories":72}]},{"name":"Sugar - Sugar Granulated, 3 tbsps","nutrients":[{"Calories":72}]},{"name":"Hersheys - Chocolate Syrup Corrected, 3 Tbsp","nutrients":[{"Calories":150}]},{"name":"Hersheys - Chocolate Syrup Corrected, 3 Tbsp","nutrients":[{"Calories":150}]}]},{"name":"lunch","dishes":[{"name":"Fresh - Hard Boiled Egg, 1 Large","nutrients":[{"Calories":80}]},{"name":"Fresh - Hard Boiled Egg, 1 Large","nutrients":[{"Calories":80}]}]}],"summary":{"total":[{"Calories":711}],"goal":[{"Calories":1450}]}},{"id":9202,"date":"2015-01-10","meals":[{"name":"lunch","dishes":[{"name":"Clover Valley - 100% Whole Wheat Bread, 2 slice","nutrients":[{"Calories":120}]},{"name":"Clover Valley - 100% Whole Wheat Bread, 2 slice","nutrients":[{"Calories":120}]},{"name":"Fresh - Hard Boiled Egg, 1 Large","nutrients":[{"Calories":80}]},{"name":"Fresh - Hard Boiled Egg, 1 Large","nutrients":[{"Calories":80}]},{"name":"T - Tomato Slice, 2 slice","nutrients":[{"Calories":10}]},{"name":"T - Tomato Slice, 2 slice","nutrients":[{"Calories":10}]},{"name":"Mayo - Mayo, 2 tbs","nutrients":[{"Calories":180}]},{"name":"Mayo - Mayo, 2 tbs","nutrients":[{"Calories":180}]}]},{"name":"snack","dishes":[{"name":"Orange - Orange - Large, 0.5 orange 340 grams","nutrients":[{"Calories":45}]},{"name":"Orange - Orange - Large, 0.5 orange 340 grams","nutrients":[{"Calories":45}]}]}],"summary":{"total":[{"Calories":435}],"goal":[{"Calories":1450}]}},{"id":9202,"date":"2015-01-11","meals":[{"name":"lunch","dishes":[{"name":"Clover Valley - 100% Whole Wheat Bread, 2 slice","nutrients":[{"Calories":120}]},{"name":"Clover Valley - 100% Whole Wheat Bread, 2 slice","nutrients":[{"Calories":120}]},{"name":"Butter - Salted, 2 tsps","nutrients":[{"Calories":68}]},{"name":"Butter - Salted, 2 tsps","nutrients":[{"Calories":68}]}]},{"name":"dinner","dishes":[{"name":"Allrecipes - Cheese Ravioli With Fresh Tomato and Artichoke Sauce, 1/6 recipe","nutrients":[{"Calories":355}]},{"name":"Allrecipes - Cheese Ravioli With Fresh Tomato and Artichoke Sauce, 1/6 recipe","nutrients":[{"Calories":355}]}]}],"summary":{"total":[{"Calories":543}],"goal":[{"Calories":1450}]}},{"id":9202,"date":"2015-01-14","meals":[{"name":"lunch","dishes":[{"name":"Clover Valley - 100% Whole Wheat Bread, 2 slice","nutrients":[{"Calories":120}]},{"name":"Clover Valley - 100% Whole Wheat Bread, 2 slice","nutrients":[{"Calories":120}]},{"name":"Mayo - Mayo, 2 tbs","nutrients":[{"Calories":180}]},{"name":"Mayo - Mayo, 2 tbs","nutrients":[{"Calories":180}]},{"name":"T - Tomato Slice, 2 slice","nutrients":[{"Calories":10}]},{"name":"T - Tomato Slice, 2 slice","nutrients":[{"Calories":10}]}]},{"name":"snack","dishes":[{"name":"Granny Smith Apple - Green Apple, Large, 1 apple 9oz/255g","nutrients":[{"Calories":110}]},{"name":"Granny Smith Apple - Green Apple, Large, 1 apple 9oz/255g","nutrients":[{"Calories":110}]}]},{"name":"dinner","dishes":[{"name":"Taste of Home - Quick Potato Corn Chowder, 3 cup","nutrients":[{"Calories":528}]},{"name":"Taste of Home - Quick Potato Corn Chowder, 3 cup","nutrients":[{"Calories":528}]}]}],"summary":{"total":[{"Calories":948}],"goal":[{"Calories":1450}]}},{"id":9202,"date":"2015-01-15","meals":[{"name":"lunch","dishes":[{"name":"Subway - 6 Turkey Breast on Honey Wheat With Provalone and Veggies, 12  sub","nutrients":[{"Calories":900}]},{"name":"Subway - 6 Turkey Breast on Honey Wheat With Provalone and Veggies, 12  sub","nutrients":[{"Calories":900}]}]},{"name":"snack","dishes":[{"name":"Bananas - Raw, 1 large 8 to 8-7/8 long","nutrients":[{"Calories":121}]},{"name":"Bananas - Raw, 1 large 8 to 8-7/8 long","nutrients":[{"Calories":121}]}]},{"name":"dinner","dishes":[{"name":"Great Value - Whole Wheat Thin Spaghetti Correct, 4 oz","nutrients":[{"Calories":360}]},{"name":"Great Value - Whole Wheat Thin Spaghetti Correct, 4 oz","nutrients":[{"Calories":360}]},{"name":"Great Value Walmart - Chunky Italian Garden Pasta Sauce Correct, 128 g 1/2 c","nutrients":[{"Calories":90}]},{"name":"Great Value Walmart - Chunky Italian Garden Pasta Sauce Correct, 128 g 1/2 c","nutrients":[{"Calories":90}]},{"name":"Generic - Eggplant, Fried and Battered, 0.15 cup","nutrients":[{"Calories":50}]},{"name":"Generic - Eggplant, Fried and Battered, 0.15 cup","nutrients":[{"Calories":50}]},{"name":"great value - whole milk, 2 cup","nutrients":[{"Calories":300}]},{"name":"great value - whole milk, 2 cup","nutrients":[{"Calories":300}]}]}],"summary":{"total":[{"Calories":1821}],"goal":[{"Calories":1450}]}},{"id":9202,"date":"2015-01-18","meals":[{"name":"breakfast","dishes":[{"name":"Homemade - American Pancake, 2 pancakes","nutrients":[{"Calories":213}]},{"name":"Homemade - American Pancake, 2 pancakes","nutrients":[{"Calories":213}]},{"name":"maple grove farms - 100% maple syrup, 1/8 cup","nutrients":[{"Calories":105}]},{"name":"maple grove farms - 100% maple syrup, 1/8 cup","nutrients":[{"Calories":105}]}]},{"name":"lunch","dishes":[{"name":"Mom's Homemade - Potato Salad~, 1/2 cup","nutrients":[{"Calories":179}]},{"name":"Mom's Homemade - Potato Salad~, 1/2 cup","nutrients":[{"Calories":179}]},{"name":"Great Value - Broccoli, 2 Cup","nutrients":[{"Calories":60}]},{"name":"Great Value - Broccoli, 2 Cup","nutrients":[{"Calories":60}]},{"name":"Butter - Salted, 1 tbsp","nutrients":[{"Calories":102}]},{"name":"Butter - Salted, 1 tbsp","nutrients":[{"Calories":102}]}]},{"name":"dinner","dishes":[{"name":"Iceburg - Lettuce, 2 cup 72g","nutrients":[{"Calories":20}]},{"name":"Iceburg - Lettuce, 2 cup 72g","nutrients":[{"Calories":20}]},{"name":"T - Tomato Slice, 34 g 3 wheels","nutrients":[{"Calories":5}]},{"name":"T - Tomato Slice, 34 g 3 wheels","nutrients":[{"Calories":5}]},{"name":"Cucumber - Peeled, raw, 0.5 cup, sliced","nutrients":[{"Calories":7}]},{"name":"Cucumber - Peeled, raw, 0.5 cup, sliced","nutrients":[{"Calories":7}]},{"name":"Onions - Sweet, raw, 0.25 onion","nutrients":[{"Calories":26}]},{"name":"Onions - Sweet, raw, 0.25 onion","nutrients":[{"Calories":26}]},{"name":"Hidden Valley - Farmhouse Originals Homestyle Italian Dressing, 2 Tbsp","nutrients":[{"Calories":100}]},{"name":"Hidden Valley - Farmhouse Originals Homestyle Italian Dressing, 2 Tbsp","nutrients":[{"Calories":100}]}]}],"summary":{"total":[{"Calories":817}],"goal":[{"Calories":1450}]}},{"id":9202,"date":"2015-01-19","meals":[{"name":"breakfast","dishes":[{"name":"General Mills - Honey Nut Cheerios - Cereal, 1 cup 28g","nutrients":[{"Calories":147}]},{"name":"General Mills - Honey Nut Cheerios - Cereal, 1 cup 28g","nutrients":[{"Calories":147}]},{"name":"great value - whole milk, 1 cup","nutrients":[{"Calories":150}]},{"name":"great value - whole milk, 1 cup","nutrients":[{"Calories":150}]}]},{"name":"lunch","dishes":[{"name":"T - Tomato Slice, 1 slice","nutrients":[{"Calories":5}]},{"name":"T - Tomato Slice, 1 slice","nutrients":[{"Calories":5}]},{"name":"Mayo - Mayo, 1 tbs","nutrients":[{"Calories":90}]},{"name":"Mayo - Mayo, 1 tbs","nutrients":[{"Calories":90}]},{"name":"Clover Valley - 100% Whole Wheat Bread, 2 slice","nutrients":[{"Calories":120}]},{"name":"Clover Valley - 100% Whole Wheat Bread, 2 slice","nutrients":[{"Calories":120}]},{"name":"Iceburg Lettuce - Lettuce, 0.25 cup 72 grams","nutrients":[{"Calories":3}]},{"name":"Iceburg Lettuce - Lettuce, 0.25 cup 72 grams","nutrients":[{"Calories":3}]},{"name":"Fresh - Hard Boiled Egg, 1 Large","nutrients":[{"Calories":80}]},{"name":"Fresh - Hard Boiled Egg, 1 Large","nutrients":[{"Calories":80}]}]},{"name":"snack","dishes":[{"name":"Brachs Candy Cane - Candy Cane, 1 piece","nutrients":[{"Calories":50}]},{"name":"Brachs Candy Cane - Candy Cane, 1 piece","nutrients":[{"Calories":50}]},{"name":"Sensible Solutions - Garden Veggie Straws - Zesty Ranch, 38 straws","nutrients":[{"Calories":130}]},{"name":"Sensible Solutions - Garden Veggie Straws - Zesty Ranch, 38 straws","nutrients":[{"Calories":130}]},{"name":"Charms - Blow Pop - Watermelon, 18 g","nutrients":[{"Calories":60}]},{"name":"Charms - Blow Pop - Watermelon, 18 g","nutrients":[{"Calories":60}]}]},{"name":"dinner","dishes":[{"name":"Great Value - Whole Wheat Thin Spaghetti Correct, 4 oz","nutrients":[{"Calories":360}]},{"name":"Great Value - Whole Wheat Thin Spaghetti Correct, 4 oz","nutrients":[{"Calories":360}]},{"name":"Great Value - Frozen Broccoli, 1.5 cup 85g","nutrients":[{"Calories":45}]},{"name":"Great Value - Frozen Broccoli, 1.5 cup 85g","nutrients":[{"Calories":45}]},{"name":"Great Value - 100% Pure Extra Virgin Olive Oil, 2 Tbsp 15mL","nutrients":[{"Calories":240}]},{"name":"Great Value - 100% Pure Extra Virgin Olive Oil, 2 Tbsp 15mL","nutrients":[{"Calories":240}]},{"name":"Onions - Sweet, raw, 0.25 onion","nutrients":[{"Calories":26}]},{"name":"Onions - Sweet, raw, 0.25 onion","nutrients":[{"Calories":26}]}]}],"summary":{"total":[{"Calories":1506}],"goal":[{"Calories":1760}]}},{"id":9202,"date":"2015-01-20","meals":[{"name":"dinner","dishes":[{"name":"Simply Nature - Organic Diced Tomatoes 28 Oz. Can, 1/2 cup","nutrients":[{"Calories":25}]},{"name":"Simply Nature - Organic Diced Tomatoes 28 Oz. Can, 1/2 cup","nutrients":[{"Calories":25}]},{"name":"Macaroni - Elbow, Cooked, 1 cup","nutrients":[{"Calories":221}]},{"name":"Macaroni - Elbow, Cooked, 1 cup","nutrients":[{"Calories":221}]},{"name":"Aldi-friendly Farms - Small Curd Cottage Cheese, 1 cup","nutrients":[{"Calories":220}]},{"name":"Aldi-friendly Farms - Small Curd Cottage Cheese, 1 cup","nutrients":[{"Calories":220}]}]}],"summary":{"total":[{"Calories":466}],"goal":[{"Calories":1450}]}},{"id":9202,"date":"2015-01-21","meals":[{"name":"breakfast","dishes":[{"name":"great value - whole milk, 1 cup","nutrients":[{"Calories":150}]},{"name":"great value - whole milk, 1 cup","nutrients":[{"Calories":150}]},{"name":"General Mills - Honey Nut Cheerios - Cereal, 1 cup 28g","nutrients":[{"Calories":147}]},{"name":"General Mills - Honey Nut Cheerios - Cereal, 1 cup 28g","nutrients":[{"Calories":147}]}]},{"name":"snack","dishes":[{"name":"Egg-Hard Boiled - 1 Egg, 1 egg","nutrients":[{"Calories":70}]},{"name":"Egg-Hard Boiled - 1 Egg, 1 egg","nutrients":[{"Calories":70}]},{"name":"Clover Valley - 100% Whole Wheat Bread, 2 slice","nutrients":[{"Calories":120}]},{"name":"Clover Valley - 100% Whole Wheat Bread, 2 slice","nutrients":[{"Calories":120}]},{"name":"Dukes - Mayo, 2 tsps","nutrients":[{"Calories":67}]},{"name":"Dukes - Mayo, 2 tsps","nutrients":[{"Calories":67}]},{"name":"Generic - Tomato, Red, Sliced, 1 slice","nutrients":[{"Calories":4}]},{"name":"Generic - Tomato, Red, Sliced, 1 slice","nutrients":[{"Calories":4}]},{"name":"Veggies - Lettuce - Iceberg, 0.5 cup","nutrients":[{"Calories":5}]},{"name":"Veggies - Lettuce - Iceberg, 0.5 cup","nutrients":[{"Calories":5}]},{"name":"Wegmans - Frozen Broccoli Florets, 1.5 cup","nutrients":[{"Calories":45}]},{"name":"Wegmans - Frozen Broccoli Florets, 1.5 cup","nutrients":[{"Calories":45}]},{"name":"Butter - Salted, 1 tbsp","nutrients":[{"Calories":102}]},{"name":"Butter - Salted, 1 tbsp","nutrients":[{"Calories":102}]}]},{"name":"snack","dishes":[{"name":"Macaroni - Elbow, Cooked, 1 cup","nutrients":[{"Calories":221}]},{"name":"Macaroni - Elbow, Cooked, 1 cup","nutrients":[{"Calories":221}]},{"name":"Hunt's - Diced Tomatoes Canned, 1/2 cup 121g","nutrients":[{"Calories":30}]},{"name":"Hunt's - Diced Tomatoes Canned, 1/2 cup 121g","nutrients":[{"Calories":30}]},{"name":"Homemade - Egg & Potato Salad, 1 Cup","nutrients":[{"Calories":275}]},{"name":"Homemade - Egg & Potato Salad, 1 Cup","nutrients":[{"Calories":275}]}]},{"name":"dinner","dishes":[{"name":"Palmer - Double Crisp Chocolate Soccer Balls, 9 pieces 40g","nutrients":[{"Calories":200}]},{"name":"Palmer - Double Crisp Chocolate Soccer Balls, 9 pieces 40g","nutrients":[{"Calories":200}]}]}],"summary":{"total":[{"Calories":1436}],"goal":[{"Calories":1706}]}},{"id":9202,"date":"2015-01-22","meals":[{"name":"breakfast","dishes":[{"name":"Friendly Farms Aldi - Milk 2% Reduced Fat-k*s, 1 cup -8 oz","nutrients":[{"Calories":130}]},{"name":"Friendly Farms Aldi - Milk 2% Reduced Fat-k*s, 1 cup -8 oz","nutrients":[{"Calories":130}]},{"name":"General Mills - Honey Nut Cheerios - Cereal, 1 cup 28g","nutrients":[{"Calories":147}]},{"name":"General Mills - Honey Nut Cheerios - Cereal, 1 cup 28g","nutrients":[{"Calories":147}]}]},{"name":"snack","dishes":[{"name":"Azteca - Small Flour Tortilla Corrected, 2 Tortillas","nutrients":[{"Calories":170}]},{"name":"Azteca - Small Flour Tortilla Corrected, 2 Tortillas","nutrients":[{"Calories":170}]},{"name":"Homemade - Refried Beans Using Pinto Beans, 8 oz","nutrients":[{"Calories":218}]},{"name":"Homemade - Refried Beans Using Pinto Beans, 8 oz","nutrients":[{"Calories":218}]},{"name":"Generic - Fresh Roma Tomatos, Medium, Diced, 0.25 cup","nutrients":[{"Calories":25}]},{"name":"Generic - Fresh Roma Tomatos, Medium, Diced, 0.25 cup","nutrients":[{"Calories":25}]},{"name":"Lettuce - Iceburg, 0.5 cup","nutrients":[{"Calories":4}]},{"name":"Lettuce - Iceburg, 0.5 cup","nutrients":[{"Calories":4}]},{"name":"Taco Bell Home Originals - Mild Taco Sauce, 2 Tsp","nutrients":[{"Calories":0}]},{"name":"Taco Bell Home Originals - Mild Taco Sauce, 2 Tsp","nutrients":[{"Calories":0}]},{"name":"Daisy - Sour Cream, 4 Tbsp 30g","nutrients":[{"Calories":120}]},{"name":"Daisy - Sour Cream, 4 Tbsp 30g","nutrients":[{"Calories":120}]},{"name":"Kraft Cracker Barrel - Sharp Cheddar Cheese, 1 oz 28g / about 1 cube","nutrients":[{"Calories":110}]},{"name":"Kraft Cracker Barrel - Sharp Cheddar Cheese, 1 oz 28g / about 1 cube","nutrients":[{"Calories":110}]}]}],"summary":{"total":[{"Calories":924}],"goal":[{"Calories":1450}]}},{"id":9202,"date":"2015-01-23","meals":[{"name":"breakfast","dishes":[{"name":"Friendly Farms Aldi - Milk 2% Reduced Fat-k*s, 1 cup -8 oz","nutrients":[{"Calories":130}]},{"name":"Friendly Farms Aldi - Milk 2% Reduced Fat-k*s, 1 cup -8 oz","nutrients":[{"Calories":130}]},{"name":"General Mills - Honey Nut Cheerios - Cereal, 1 cup 28g","nutrients":[{"Calories":147}]},{"name":"General Mills - Honey Nut Cheerios - Cereal, 1 cup 28g","nutrients":[{"Calories":147}]}]},{"name":"snack","dishes":[{"name":"Azteca - Small Flour Tortilla Corrected, 1 Tortillas","nutrients":[{"Calories":85}]},{"name":"Azteca - Small Flour Tortilla Corrected, 1 Tortillas","nutrients":[{"Calories":85}]},{"name":"Daisy - Sour Cream, 4 Tbsp 30g","nutrients":[{"Calories":120}]},{"name":"Daisy - Sour Cream, 4 Tbsp 30g","nutrients":[{"Calories":120}]},{"name":"Homemade - Refried Beans Using Pinto Beans, 8 oz","nutrients":[{"Calories":218}]},{"name":"Homemade - Refried Beans Using Pinto Beans, 8 oz","nutrients":[{"Calories":218}]},{"name":"Kraft Cracker Barrel - Sharp Cheddar Cheese, 1 oz 28g / about 1 cube","nutrients":[{"Calories":110}]},{"name":"Kraft Cracker Barrel - Sharp Cheddar Cheese, 1 oz 28g / about 1 cube","nutrients":[{"Calories":110}]},{"name":"Lettuce - Iceburg, 0.5 cup","nutrients":[{"Calories":4}]},{"name":"Lettuce - Iceburg, 0.5 cup","nutrients":[{"Calories":4}]},{"name":"Taco Bell Home Originals - Mild Taco Sauce, 4 Tsp","nutrients":[{"Calories":0}]},{"name":"Taco Bell Home Originals - Mild Taco Sauce, 4 Tsp","nutrients":[{"Calories":0}]},{"name":"Taco Bell - Home Originals - Hard Shell Shell Only, 3 shells","nutrients":[{"Calories":150}]},{"name":"Taco Bell - Home Originals - Hard Shell Shell Only, 3 shells","nutrients":[{"Calories":150}]}]}],"summary":{"total":[{"Calories":964}],"goal":[{"Calories":1450}]}},{"id":9202,"date":"2015-01-24","meals":[{"name":"snack","dishes":[{"name":"Homemade - Healthy Turkey Chili, 1 cup","nutrients":[{"Calories":264}]},{"name":"Homemade - Healthy Turkey Chili, 1 cup","nutrients":[{"Calories":264}]},{"name":"Food Network - Alex Guarnaschelli's Cast-Iron Skillet Corn Bread, 1 slice 105 g","nutrients":[{"Calories":273}]},{"name":"Food Network - Alex Guarnaschelli's Cast-Iron Skillet Corn Bread, 1 slice 105 g","nutrients":[{"Calories":273}]}]}],"summary":{"total":[{"Calories":537}],"goal":[{"Calories":1450}]}},{"id":9202,"date":"2015-01-25","meals":[{"name":"breakfast","dishes":[{"name":"Friendly Farms Aldi - Milk 2% Reduced Fat-k*s, 1 cup -8 oz","nutrients":[{"Calories":130}]},{"name":"Friendly Farms Aldi - Milk 2% Reduced Fat-k*s, 1 cup -8 oz","nutrients":[{"Calories":130}]},{"name":"General Mills - Honey Nut Cheerios - Cereal, 1 cup 28g","nutrients":[{"Calories":147}]},{"name":"General Mills - Honey Nut Cheerios - Cereal, 1 cup 28g","nutrients":[{"Calories":147}]}]},{"name":"snack","dishes":[{"name":"Smuckers - Creamy Natural Peanut Butter, 2 tbsp","nutrients":[{"Calories":210}]},{"name":"Smuckers - Creamy Natural Peanut Butter, 2 tbsp","nutrients":[{"Calories":210}]},{"name":"Smuckers - Natural Strawberry Spread, 1 tbls","nutrients":[{"Calories":30}]},{"name":"Smuckers - Natural Strawberry Spread, 1 tbls","nutrients":[{"Calories":30}]},{"name":"cover valley - 100 whole wheat bread, 2 slices","nutrients":[{"Calories":120}]},{"name":"cover valley - 100 whole wheat bread, 2 slices","nutrients":[{"Calories":120}]}]},{"name":"lunch","dishes":[{"name":"Aldi - Friendly Farms - Strawberry Banana Yogurt, 6 oz","nutrients":[{"Calories":160}]},{"name":"Aldi - Friendly Farms - Strawberry Banana Yogurt, 6 oz","nutrients":[{"Calories":160}]},{"name":"Kind Healthy Grains - Granola, Oats and Honey Clusters, 1/3 cup","nutrients":[{"Calories":130}]},{"name":"Kind Healthy Grains - Granola, Oats and Honey Clusters, 1/3 cup","nutrients":[{"Calories":130}]}]}],"summary":{"total":[{"Calories":927}],"goal":[{"Calories":1450}]}},{"id":9202,"date":"2015-01-26","meals":[{"name":"breakfast","dishes":[{"name":"Aldi - Friendly Farms - Strawberry Banana Yogurt, 6 oz","nutrients":[{"Calories":160}]},{"name":"Aldi - Friendly Farms - Strawberry Banana Yogurt, 6 oz","nutrients":[{"Calories":160}]},{"name":"Kind - Oats and Honey Clusters, 1/3 cup","nutrients":[{"Calories":130}]},{"name":"Kind - Oats and Honey Clusters, 1/3 cup","nutrients":[{"Calories":130}]}]},{"name":"snack","dishes":[{"name":"Aldi Fit & Active - Whole Wheat Thin Spaghetti-True Values, 2 oz dry, about 1/6 package","nutrients":[{"Calories":200}]},{"name":"Aldi Fit & Active - Whole Wheat Thin Spaghetti-True Values, 2 oz dry, about 1/6 package","nutrients":[{"Calories":200}]},{"name":"Walmart Great Value - Spaghetti Sauce Chunky Mushroom & Green Peppers, 1/2 cup","nutrients":[{"Calories":80}]},{"name":"Walmart Great Value - Spaghetti Sauce Chunky Mushroom & Green Peppers, 1/2 cup","nutrients":[{"Calories":80}]}]},{"name":"dinner","dishes":[{"name":"Breyers All Natural Ice Cream - Vanilla, Chocolate, 1/2 cup","nutrients":[{"Calories":130}]},{"name":"Breyers All Natural Ice Cream - Vanilla, Chocolate, 1/2 cup","nutrients":[{"Calories":130}]}]}],"summary":{"total":[{"Calories":700}],"goal":[{"Calories":1450}]}},{"id":9202,"date":"2015-01-27","meals":[{"name":"breakfast","dishes":[{"name":"great value - whole milk, 1 cup","nutrients":[{"Calories":150}]},{"name":"great value - whole milk, 1 cup","nutrients":[{"Calories":150}]},{"name":"General Mills - Honey Nut Cheerios - Cereal, 1 cup 28g","nutrients":[{"Calories":147}]},{"name":"General Mills - Honey Nut Cheerios - Cereal, 1 cup 28g","nutrients":[{"Calories":147}]}]},{"name":"snack","dishes":[{"name":"Aldi Fit & Active - Whole Wheat Thin Spaghetti-True Values, 2 oz dry, about 1/6 package","nutrients":[{"Calories":200}]},{"name":"Aldi Fit & Active - Whole Wheat Thin Spaghetti-True Values, 2 oz dry, about 1/6 package","nutrients":[{"Calories":200}]},{"name":"Walmart Great Value - Spaghetti Sauce Chunky Mushroom & Green Peppers, 1/2 cup","nutrients":[{"Calories":80}]},{"name":"Walmart Great Value - Spaghetti Sauce Chunky Mushroom & Green Peppers, 1/2 cup","nutrients":[{"Calories":80}]},{"name":"Great Value Walmart - 100% Whole Wheat Bread, 1 slice","nutrients":[{"Calories":60}]},{"name":"Great Value Walmart - 100% Whole Wheat Bread, 1 slice","nutrients":[{"Calories":60}]}]}],"summary":{"total":[{"Calories":637}],"goal":[{"Calories":1450}]}},{"id":9202,"date":"2015-01-28","meals":[{"name":"snack","dishes":[{"name":"Austin - Toasty Crackers With Peanut Butter 6 Pack, 1 Package 6 crackers","nutrients":[{"Calories":190}]},{"name":"Austin - Toasty Crackers With Peanut Butter 6 Pack, 1 Package 6 crackers","nutrients":[{"Calories":190}]}]}],"summary":{"total":[{"Calories":190}],"goal":[{"Calories":1450}]}},{"id":9202,"date":"2015-01-30","meals":[{"name":"breakfast","dishes":[{"name":"great value - whole milk, 1 cup","nutrients":[{"Calories":150}]},{"name":"great value - whole milk, 1 cup","nutrients":[{"Calories":150}]},{"name":"General Mills - Honey Nut Cheerio's, 1 cup","nutrients":[{"Calories":147}]},{"name":"General Mills - Honey Nut Cheerio's, 1 cup","nutrients":[{"Calories":147}]}]},{"name":"snack","dishes":[{"name":"Aldi Burman's - Yellow Mustard, 1 tsp.","nutrients":[{"Calories":0}]},{"name":"Aldi Burman's - Yellow Mustard, 1 tsp.","nutrients":[{"Calories":0}]},{"name":"T - Tomato Slice, 2 slices","nutrients":[{"Calories":3}]},{"name":"T - Tomato Slice, 2 slices","nutrients":[{"Calories":3}]},{"name":"Oscar Mayer - Deli Fresh - Oven Roasted Turkey Breast, 2 oz 56g","nutrients":[{"Calories":50}]},{"name":"Oscar Mayer - Deli Fresh - Oven Roasted Turkey Breast, 2 oz 56g","nutrients":[{"Calories":50}]},{"name":"Aldi L'oven Fresh - 100% Whole Wheat Bread; 22g Whole Grains, 2 slice","nutrients":[{"Calories":200}]},{"name":"Aldi L'oven Fresh - 100% Whole Wheat Bread; 22g Whole Grains, 2 slice","nutrients":[{"Calories":200}]}]}],"summary":{"total":[{"Calories":550}],"goal":[{"Calories":1450}]}},{"id":9202,"date":"2015-02-01","meals":[{"name":"snack","dishes":[{"name":"Chinese - General Tso's Chicken, 0.5 cup","nutrients":[{"Calories":147}]},{"name":"Chinese - General Tso's Chicken, 0.5 cup","nutrients":[{"Calories":147}]}]},{"name":"snack","dishes":[{"name":"Chicken Leg - Medium - Baked, 1 leg","nutrients":[{"Calories":111}]},{"name":"Chicken Leg - Medium - Baked, 1 leg","nutrients":[{"Calories":111}]},{"name":"Mashed Potatoes - Homemade, 1/2 cup","nutrients":[{"Calories":80}]},{"name":"Mashed Potatoes - Homemade, 1/2 cup","nutrients":[{"Calories":80}]},{"name":"Food Network - Alex Guarnaschelli's Cast-Iron Skillet Corn Bread, 1 slice 105 g","nutrients":[{"Calories":273}]},{"name":"Food Network - Alex Guarnaschelli's Cast-Iron Skillet Corn Bread, 1 slice 105 g","nutrients":[{"Calories":273}]},{"name":"Butter - Salted, 1 tbsp","nutrients":[{"Calories":102}]},{"name":"Butter - Salted, 1 tbsp","nutrients":[{"Calories":102}]}]}],"summary":{"total":[{"Calories":713}],"goal":[{"Calories":1450}]}},{"id":9202,"date":"2015-02-02","meals":[{"name":"breakfast","dishes":[{"name":"General Mills - Honey Nut Cheerio's, 1 cup","nutrients":[{"Calories":147}]},{"name":"General Mills - Honey Nut Cheerio's, 1 cup","nutrients":[{"Calories":147}]},{"name":"great value - whole milk, 0.5 cup","nutrients":[{"Calories":75}]},{"name":"great value - whole milk, 0.5 cup","nutrients":[{"Calories":75}]}]}],"summary":{"total":[{"Calories":222}],"goal":[{"Calories":1450}]}},{"id":9202,"date":"2015-02-13","meals":[{"name":"snack","dishes":[{"name":"Bear Naked - Fruit and Nutty Layered Granola Bar, 1 bar","nutrients":[{"Calories":170}]},{"name":"Bear Naked - Fruit and Nutty Layered Granola Bar, 1 bar","nutrients":[{"Calories":170}]}]},{"name":"lunch","dishes":[{"name":"Loven Fresh - 100% Whole Wheat Bread Whole Grain, 2 slice","nutrients":[{"Calories":200}]},{"name":"Loven Fresh - 100% Whole Wheat Bread Whole Grain, 2 slice","nutrients":[{"Calories":200}]},{"name":"Burman's - Aldi - Honey Mustard Correct, 2 tsp. 5g","nutrients":[{"Calories":10}]},{"name":"Burman's - Aldi - Honey Mustard Correct, 2 tsp. 5g","nutrients":[{"Calories":10}]},{"name":"Sara Lee - Oven Roasted Turkey Deli Meat, 5 oz","nutrients":[{"Calories":150}]},{"name":"Sara Lee - Oven Roasted Turkey Deli Meat, 5 oz","nutrients":[{"Calories":150}]},{"name":"Frigo - Cheesehead String Cheese, 1 piece 28g","nutrients":[{"Calories":80}]},{"name":"Frigo - Cheesehead String Cheese, 1 piece 28g","nutrients":[{"Calories":80}]}]}],"summary":{"total":[{"Calories":610}],"goal":[{"Calories":1450}]}},{"id":9202,"date":"2015-02-16","meals":[{"name":"snack","dishes":[{"name":"Aldi - Friendly Farms - Strawberry Banana Yogurt, 6 oz","nutrients":[{"Calories":160}]},{"name":"Aldi - Friendly Farms - Strawberry Banana Yogurt, 6 oz","nutrients":[{"Calories":160}]}]},{"name":"lunch","dishes":[{"name":"Loven Fresh - 100% Whole Wheat Bread Whole Grain, 2 slice","nutrients":[{"Calories":200}]},{"name":"Loven Fresh - 100% Whole Wheat Bread Whole Grain, 2 slice","nutrients":[{"Calories":200}]},{"name":"Sara Lee - Oven Roasted Turkey Deli Meat, 2 oz","nutrients":[{"Calories":60}]},{"name":"Sara Lee - Oven Roasted Turkey Deli Meat, 2 oz","nutrients":[{"Calories":60}]},{"name":"Frigo - Cheesehead String Cheese, 1 piece 28g","nutrients":[{"Calories":80}]},{"name":"Frigo - Cheesehead String Cheese, 1 piece 28g","nutrients":[{"Calories":80}]},{"name":"Burman's - Aldi - Honey Mustard Correct, 2 tsp. 5g","nutrients":[{"Calories":10}]},{"name":"Burman's - Aldi - Honey Mustard Correct, 2 tsp. 5g","nutrients":[{"Calories":10}]}]},{"name":"snack","dishes":[{"name":"Fresh - Strawberries - Cut In Halves, 1 Cup","nutrients":[{"Calories":46}]},{"name":"Fresh - Strawberries - Cut In Halves, 1 Cup","nutrients":[{"Calories":46}]},{"name":"Ferrero - Nutella 1 Tablespoon, 1 tablespoon","nutrients":[{"Calories":100}]},{"name":"Ferrero - Nutella 1 Tablespoon, 1 tablespoon","nutrients":[{"Calories":100}]}]},{"name":"dinner","dishes":[{"name":"Chicken - Breast, meat only, cooked, roasted, 5 ozs","nutrients":[{"Calories":234}]},{"name":"Chicken - Breast, meat only, cooked, roasted, 5 ozs","nutrients":[{"Calories":234}]},{"name":"Cucumber - Peeled, raw, 0.5 cup, sliced","nutrients":[{"Calories":7}]},{"name":"Cucumber - Peeled, raw, 0.5 cup, sliced","nutrients":[{"Calories":7}]},{"name":"Iceburg - Lettuce, 1 cup 72g","nutrients":[{"Calories":10}]},{"name":"Iceburg - Lettuce, 1 cup 72g","nutrients":[{"Calories":10}]},{"name":"T - Tomato Slice, 34 g 3 wheels","nutrients":[{"Calories":5}]},{"name":"T - Tomato Slice, 34 g 3 wheels","nutrients":[{"Calories":5}]},{"name":"Litehouse - Homestyle Ranch Dressing, 2 Tbsp.","nutrients":[{"Calories":120}]},{"name":"Litehouse - Homestyle Ranch Dressing, 2 Tbsp.","nutrients":[{"Calories":120}]}]}],"summary":{"total":[{"Calories":1032}],"goal":[{"Calories":1450}]}},{"id":9202,"date":"2015-02-17","meals":[{"name":"breakfast","dishes":[{"name":"Kind - Oats and Honey Clusters, 1/3 cup","nutrients":[{"Calories":130}]},{"name":"Kind - Oats and Honey Clusters, 1/3 cup","nutrients":[{"Calories":130}]},{"name":"Friendly Farms - Strawberry Lowfat Yogurt, 6 oz 170g","nutrients":[{"Calories":160}]},{"name":"Friendly Farms - Strawberry Lowfat Yogurt, 6 oz 170g","nutrients":[{"Calories":160}]}]},{"name":"snack","dishes":[{"name":"Frigo - Cheesehead String Cheese, 1 piece 28g","nutrients":[{"Calories":80}]},{"name":"Frigo - Cheesehead String Cheese, 1 piece 28g","nutrients":[{"Calories":80}]}]},{"name":"lunch","dishes":[{"name":"Burman's - Aldi - Honey Mustard Correct, 2 tsp. 5g","nutrients":[{"Calories":10}]},{"name":"Burman's - Aldi - Honey Mustard Correct, 2 tsp. 5g","nutrients":[{"Calories":10}]},{"name":"Cucumber - With peel, raw, 0.5 cup slices","nutrients":[{"Calories":8}]},{"name":"Cucumber - With peel, raw, 0.5 cup slices","nutrients":[{"Calories":8}]},{"name":"Loven Fresh - 100% Whole Wheat Bread Whole Grain, 2 slice","nutrients":[{"Calories":200}]},{"name":"Loven Fresh - 100% Whole Wheat Bread Whole Grain, 2 slice","nutrients":[{"Calories":200}]},{"name":"Sara Lee - Oven Roasted Turkey Deli Meat, 2 oz","nutrients":[{"Calories":60}]},{"name":"Sara Lee - Oven Roasted Turkey Deli Meat, 2 oz","nutrients":[{"Calories":60}]},{"name":"Alpine Lace - 25% Reduced Fat Swiss Cheese, 1 Slice","nutrients":[{"Calories":70}]},{"name":"Alpine Lace - 25% Reduced Fat Swiss Cheese, 1 Slice","nutrients":[{"Calories":70}]}]},{"name":"snack","dishes":[{"name":"Halo - Mandarin Oranges, 2 Oranges","nutrients":[{"Calories":80}]},{"name":"Halo - Mandarin Oranges, 2 Oranges","nutrients":[{"Calories":80}]}]},{"name":"dinner","dishes":[{"name":"Cucumber - Peeled, raw, 0.5 cup, sliced","nutrients":[{"Calories":7}]},{"name":"Cucumber - Peeled, raw, 0.5 cup, sliced","nutrients":[{"Calories":7}]},{"name":"Iceburg - Lettuce, 1 cup 72g","nutrients":[{"Calories":10}]},{"name":"Iceburg - Lettuce, 1 cup 72g","nutrients":[{"Calories":10}]},{"name":"Litehouse - Homestyle Ranch Dressing, 2 Tbsp.","nutrients":[{"Calories":120}]},{"name":"Litehouse - Homestyle Ranch Dressing, 2 Tbsp.","nutrients":[{"Calories":120}]},{"name":"T - Tomato Slice, 34 g 3 wheels","nutrients":[{"Calories":5}]},{"name":"T - Tomato Slice, 34 g 3 wheels","nutrients":[{"Calories":5}]},{"name":"Sara Lee - Oven Roasted Turkey Deli Meat, 5 oz","nutrients":[{"Calories":150}]},{"name":"Sara Lee - Oven Roasted Turkey Deli Meat, 5 oz","nutrients":[{"Calories":150}]},{"name":"Fresh Attitude - Baby Spinich, 1 cups","nutrients":[{"Calories":5}]},{"name":"Fresh Attitude - Baby Spinich, 1 cups","nutrients":[{"Calories":5}]}]}],"summary":{"total":[{"Calories":1095}],"goal":[{"Calories":1450}]}},{"id":9202,"date":"2015-02-18","meals":[{"name":"snack","dishes":[{"name":"Bear Naked - Fruit and Nutty Layered Granola Bar, 1 bar","nutrients":[{"Calories":170}]},{"name":"Bear Naked - Fruit and Nutty Layered Granola Bar, 1 bar","nutrients":[{"Calories":170}]}]},{"name":"lunch","dishes":[{"name":"Burman's - Aldi - Honey Mustard Correct, 4 tsp. 5g","nutrients":[{"Calories":20}]},{"name":"Burman's - Aldi - Honey Mustard Correct, 4 tsp. 5g","nutrients":[{"Calories":20}]},{"name":"Loven Fresh - 100% Whole Wheat Bread Whole Grain, 2 slice","nutrients":[{"Calories":200}]},{"name":"Loven Fresh - 100% Whole Wheat Bread Whole Grain, 2 slice","nutrients":[{"Calories":200}]},{"name":"Sara Lee - Oven Roasted Turkey Deli Meat, 2 oz","nutrients":[{"Calories":60}]},{"name":"Sara Lee - Oven Roasted Turkey Deli Meat, 2 oz","nutrients":[{"Calories":60}]},{"name":"Fresh - Hard Boiled Egg, 1 Large","nutrients":[{"Calories":80}]},{"name":"Fresh - Hard Boiled Egg, 1 Large","nutrients":[{"Calories":80}]}]},{"name":"snack","dishes":[{"name":"Homemade - Chocolate Covered Strawberry, 4 Large Berry","nutrients":[{"Calories":240}]},{"name":"Homemade - Chocolate Covered Strawberry, 4 Large Berry","nutrients":[{"Calories":240}]}]},{"name":"dinner","dishes":[{"name":"Cucumber - Peeled, raw, 0.5 cup, sliced","nutrients":[{"Calories":7}]},{"name":"Cucumber - Peeled, raw, 0.5 cup, sliced","nutrients":[{"Calories":7}]},{"name":"Egg - Hard Boiled - Large, 1 Egg","nutrients":[{"Calories":78}]},{"name":"Egg - Hard Boiled - Large, 1 Egg","nutrients":[{"Calories":78}]},{"name":"Fresh Attitude - Baby Spinich, 1 cups","nutrients":[{"Calories":5}]},{"name":"Fresh Attitude - Baby Spinich, 1 cups","nutrients":[{"Calories":5}]},{"name":"Sara Lee - Oven Roasted Turkey Deli Meat, 3 oz","nutrients":[{"Calories":90}]},{"name":"Sara Lee - Oven Roasted Turkey Deli Meat, 3 oz","nutrients":[{"Calories":90}]},{"name":"T - Tomato Slice, 34 g 3 wheels","nutrients":[{"Calories":5}]},{"name":"T - Tomato Slice, 34 g 3 wheels","nutrients":[{"Calories":5}]},{"name":"Iceburg - Lettuce, 1 cup 72g","nutrients":[{"Calories":10}]},{"name":"Iceburg - Lettuce, 1 cup 72g","nutrients":[{"Calories":10}]},{"name":"Litehouse - Homestyle Ranch Dressing, 3 Tbsp.","nutrients":[{"Calories":180}]},{"name":"Litehouse - Homestyle Ranch Dressing, 3 Tbsp.","nutrients":[{"Calories":180}]}]}],"summary":{"total":[{"Calories":1145}],"goal":[{"Calories":1450}]}},{"id":9202,"date":"2015-02-20","meals":[{"name":"breakfast","dishes":[{"name":"Aldi Friendly Farms - Lowfat Blueberry Yogurt, 1 container","nutrients":[{"Calories":160}]},{"name":"Aldi Friendly Farms - Lowfat Blueberry Yogurt, 1 container","nutrients":[{"Calories":160}]}]},{"name":"snack","dishes":[{"name":"Bear Naked - Fruit and Nutty Layered Granola Bar, 1 bar","nutrients":[{"Calories":170}]},{"name":"Bear Naked - Fruit and Nutty Layered Granola Bar, 1 bar","nutrients":[{"Calories":170}]}]},{"name":"lunch","dishes":[{"name":"Sprite- - 12 Oz. Can, 0.5 Can- 12 oz.","nutrients":[{"Calories":70}]},{"name":"Sprite- - 12 Oz. Can, 0.5 Can- 12 oz.","nutrients":[{"Calories":70}]}]},{"name":"dinner","dishes":[{"name":"Hebrew National - Beef Hot Dog, 1 Hot Dog","nutrients":[{"Calories":150}]},{"name":"Hebrew National - Beef Hot Dog, 1 Hot Dog","nutrients":[{"Calories":150}]},{"name":"Great Value - Whole Wheat Hot Dog Bun, 1 bun 50 g=1.75 oz","nutrients":[{"Calories":120}]},{"name":"Great Value - Whole Wheat Hot Dog Bun, 1 bun 50 g=1.75 oz","nutrients":[{"Calories":120}]},{"name":"Aldi - Clancy's - Kettle Chips-mesquite Bbq, 12 chips 28g","nutrients":[{"Calories":150}]},{"name":"Aldi - Clancy's - Kettle Chips-mesquite Bbq, 12 chips 28g","nutrients":[{"Calories":150}]},{"name":"Aldi Burman's - Yellow Mustard, 1 tsp.","nutrients":[{"Calories":0}]},{"name":"Aldi Burman's - Yellow Mustard, 1 tsp.","nutrients":[{"Calories":0}]}]}],"summary":{"total":[{"Calories":820}],"goal":[{"Calories":1450}]}},{"id":9202,"date":"2015-02-21","meals":[{"name":"breakfast","dishes":[{"name":"great value - whole milk, 1 cup","nutrients":[{"Calories":150}]},{"name":"great value - whole milk, 1 cup","nutrients":[{"Calories":150}]},{"name":"General Mills - Honey Nut Cheerio's, 1 cup","nutrients":[{"Calories":147}]},{"name":"General Mills - Honey Nut Cheerio's, 1 cup","nutrients":[{"Calories":147}]},{"name":"Bananas - Raw, 1 large 8 to 8-7/8 long","nutrients":[{"Calories":121}]},{"name":"Bananas - Raw, 1 large 8 to 8-7/8 long","nutrients":[{"Calories":121}]}]},{"name":"lunch","dishes":[{"name":"Alpine Lace - 25% Reduced Fat Swiss Cheese, 1 Slice","nutrients":[{"Calories":70}]},{"name":"Alpine Lace - 25% Reduced Fat Swiss Cheese, 1 Slice","nutrients":[{"Calories":70}]},{"name":"Burman's - Aldi - Honey Mustard Correct, 4 tsp. 5g","nutrients":[{"Calories":20}]},{"name":"Burman's - Aldi - Honey Mustard Correct, 4 tsp. 5g","nutrients":[{"Calories":20}]},{"name":"Loven Fresh - 100% Whole Wheat Bread Whole Grain, 2 slice","nutrients":[{"Calories":200}]},{"name":"Loven Fresh - 100% Whole Wheat Bread Whole Grain, 2 slice","nutrients":[{"Calories":200}]},{"name":"Sara Lee - Low-Sodium Roast Beef-Deli, 2 oz","nutrients":[{"Calories":70}]},{"name":"Sara Lee - Low-Sodium Roast Beef-Deli, 2 oz","nutrients":[{"Calories":70}]}]},{"name":"snack","dishes":[{"name":"Halo - Mandarin Oranges, 1 Oranges","nutrients":[{"Calories":40}]},{"name":"Halo - Mandarin Oranges, 1 Oranges","nutrients":[{"Calories":40}]}]},{"name":"dinner","dishes":[{"name":"Aldi Burman's - Yellow Mustard, 1 tsp.","nutrients":[{"Calories":0}]},{"name":"Aldi Burman's - Yellow Mustard, 1 tsp.","nutrients":[{"Calories":0}]},{"name":"Hebrew National - Beef Hot Dog, 2 Hot Dog","nutrients":[{"Calories":300}]},{"name":"Hebrew National - Beef Hot Dog, 2 Hot Dog","nutrients":[{"Calories":300}]},{"name":"Generic - Homemade Macaroni and Cheese, 1.5 cup","nutrients":[{"Calories":338}]},{"name":"Generic - Homemade Macaroni and Cheese, 1.5 cup","nutrients":[{"Calories":338}]},{"name":"Soda, Sprite - Soda, Sprite, 12 oz","nutrients":[{"Calories":140}]},{"name":"Soda, Sprite - Soda, Sprite, 12 oz","nutrients":[{"Calories":140}]},{"name":"Strawberries - Raw, 1 cup, halves","nutrients":[{"Calories":49}]},{"name":"Strawberries - Raw, 1 cup, halves","nutrients":[{"Calories":49}]},{"name":"Aldi Baker's Corner - Milk Chocolate Chips, 6 tbsp 14 g","nutrients":[{"Calories":420}]},{"name":"Aldi Baker's Corner - Milk Chocolate Chips, 6 tbsp 14 g","nutrients":[{"Calories":420}]}]}],"summary":{"total":[{"Calories":2065}],"goal":[{"Calories":1734}]}},{"id":9202,"date":"2015-02-22","meals":[{"name":"breakfast","dishes":[{"name":"Bananas - Raw, 0.5 large 8 to 8-7/8 long","nutrients":[{"Calories":61}]},{"name":"Bananas - Raw, 0.5 large 8 to 8-7/8 long","nutrients":[{"Calories":61}]}]},{"name":"snack","dishes":[{"name":"Generic - Chocolate Peanut Butter Ball, 1 ball","nutrients":[{"Calories":103}]},{"name":"Generic - Chocolate Peanut Butter Ball, 1 ball","nutrients":[{"Calories":103}]}]},{"name":"lunch","dishes":[{"name":"Toufayan - Pita Bread Whole Wheat, 1 loaf 56 g","nutrients":[{"Calories":150}]},{"name":"Toufayan - Pita Bread Whole Wheat, 1 loaf 56 g","nutrients":[{"Calories":150}]},{"name":"Sara Lee - Low-Sodium Roast Beef-Deli, 3 oz","nutrients":[{"Calories":105}]},{"name":"Sara Lee - Low-Sodium Roast Beef-Deli, 3 oz","nutrients":[{"Calories":105}]},{"name":"Alpine Lace - 25% Reduced Fat Swiss Cheese, 1 Slice","nutrients":[{"Calories":70}]},{"name":"Alpine Lace - 25% Reduced Fat Swiss Cheese, 1 Slice","nutrients":[{"Calories":70}]},{"name":"Cucumber - With peel, raw, 0.13 cup slices","nutrients":[{"Calories":2}]},{"name":"Cucumber - With peel, raw, 0.13 cup slices","nutrients":[{"Calories":2}]},{"name":"Mayo - Mayo, 1 tbs","nutrients":[{"Calories":90}]},{"name":"Mayo - Mayo, 1 tbs","nutrients":[{"Calories":90}]},{"name":"T - Tomato Slice, 3 slices","nutrients":[{"Calories":5}]},{"name":"T - Tomato Slice, 3 slices","nutrients":[{"Calories":5}]},{"name":"God's - Grapes - Green - Seedless, 1 Cup","nutrients":[{"Calories":110}]},{"name":"God's - Grapes - Green - Seedless, 1 Cup","nutrients":[{"Calories":110}]}]},{"name":"dinner","dishes":[{"name":"Biggest Loser Flavors of the World - Three Cheese Spinach Lasagna, 1 square","nutrients":[{"Calories":257}]},{"name":"Biggest Loser Flavors of the World - Three Cheese Spinach Lasagna, 1 square","nutrients":[{"Calories":257}]},{"name":"Litehouse - Homestyle Ranch Dressing, 1 Tbsp.","nutrients":[{"Calories":60}]},{"name":"Litehouse - Homestyle Ranch Dressing, 1 Tbsp.","nutrients":[{"Calories":60}]},{"name":"Iceburg - Lettuce, 0.5 cup 72g","nutrients":[{"Calories":5}]},{"name":"Iceburg - Lettuce, 0.5 cup 72g","nutrients":[{"Calories":5}]},{"name":"T - Tomato Slice, 34 g 3 wheels","nutrients":[{"Calories":5}]},{"name":"T - Tomato Slice, 34 g 3 wheels","nutrients":[{"Calories":5}]},{"name":"Fresh Attitude - Baby Spinich, 0.5 cups","nutrients":[{"Calories":3}]},{"name":"Fresh Attitude - Baby Spinich, 0.5 cups","nutrients":[{"Calories":3}]},{"name":"Cucumber - Peeled, raw, 0.25 cup, sliced","nutrients":[{"Calories":4}]},{"name":"Cucumber - Peeled, raw, 0.25 cup, sliced","nutrients":[{"Calories":4}]}]}],"summary":{"total":[{"Calories":1030}],"goal":[{"Calories":1430}]}},{"id":9202,"date":"2015-02-23","meals":[{"name":"lunch","dishes":[{"name":"Coke Life - Drink, 1 bottle 8 fl. oz. 257 ml.","nutrients":[{"Calories":60}]},{"name":"Coke Life - Drink, 1 bottle 8 fl. oz. 257 ml.","nutrients":[{"Calories":60}]}]},{"name":"dinner","dishes":[{"name":"Aldi Baker's Corner - Milk Chocolate Chips, 6 tbsp 14 g","nutrients":[{"Calories":420}]},{"name":"Aldi Baker's Corner - Milk Chocolate Chips, 6 tbsp 14 g","nutrients":[{"Calories":420}]},{"name":"Strawberries - Raw, 1 cup, halves","nutrients":[{"Calories":49}]},{"name":"Strawberries - Raw, 1 cup, halves","nutrients":[{"Calories":49}]},{"name":"Hebrew National - Beef Hot Dog, 2 Hot Dog","nutrients":[{"Calories":300}]},{"name":"Hebrew National - Beef Hot Dog, 2 Hot Dog","nutrients":[{"Calories":300}]},{"name":"Soda, Sprite - Soda, Sprite, 12 oz","nutrients":[{"Calories":140}]},{"name":"Soda, Sprite - Soda, Sprite, 12 oz","nutrients":[{"Calories":140}]},{"name":"Generic - Homemade Macaroni and Cheese, 1.13 cup","nutrients":[{"Calories":254}]},{"name":"Generic - Homemade Macaroni and Cheese, 1.13 cup","nutrients":[{"Calories":254}]},{"name":"Generic - Homemade Peanut Butter Balls, 6 ball","nutrients":[{"Calories":618}]},{"name":"Generic - Homemade Peanut Butter Balls, 6 ball","nutrients":[{"Calories":618}]}]}],"summary":{"total":[{"Calories":1841}],"goal":[{"Calories":1430}]}},{"id":9202,"date":"2015-02-24","meals":[{"name":"breakfast","dishes":[{"name":"Generic - Omlet - 2 Egg - Plain, 2 eggs","nutrients":[{"Calories":144}]},{"name":"Generic - Omlet - 2 Egg - Plain, 2 eggs","nutrients":[{"Calories":144}]},{"name":"Homemade - Sauteed Peppers, Onion and Mushrooms, 1/4 cup","nutrients":[{"Calories":30}]},{"name":"Homemade - Sauteed Peppers, Onion and Mushrooms, 1/4 cup","nutrients":[{"Calories":30}]},{"name":"Generic - Green Seedless Grape, 1 cup","nutrients":[{"Calories":104}]},{"name":"Generic - Green Seedless Grape, 1 cup","nutrients":[{"Calories":104}]}]},{"name":"snack","dishes":[{"name":"Bear Naked - Nutty Double Chocolate Layered Granola Bar, 1 Bar","nutrients":[{"Calories":190}]},{"name":"Bear Naked - Nutty Double Chocolate Layered Granola Bar, 1 Bar","nutrients":[{"Calories":190}]}]},{"name":"snack","dishes":[{"name":"Fresh - Strawberries - Cut In Halves, 1 Cup","nutrients":[{"Calories":46}]},{"name":"Fresh - Strawberries - Cut In Halves, 1 Cup","nutrients":[{"Calories":46}]},{"name":"Frigo - Cheesehead String Cheese, 1.75 piece 28g","nutrients":[{"Calories":140}]},{"name":"Frigo - Cheesehead String Cheese, 1.75 piece 28g","nutrients":[{"Calories":140}]}]},{"name":"dinner","dishes":[{"name":"Biggest Loser's Flavors of the World Cook Book - Spaghetti and Meatballs, 1/4 of recipe","nutrients":[{"Calories":398}]},{"name":"Biggest Loser's Flavors of the World Cook Book - Spaghetti and Meatballs, 1/4 of recipe","nutrients":[{"Calories":398}]},{"name":"Cucumber - Peeled, raw, 0.25 cup, sliced","nutrients":[{"Calories":4}]},{"name":"Cucumber - Peeled, raw, 0.25 cup, sliced","nutrients":[{"Calories":4}]},{"name":"Fresh Attitude - Baby Spinich, 0.5 cups","nutrients":[{"Calories":3}]},{"name":"Fresh Attitude - Baby Spinich, 0.5 cups","nutrients":[{"Calories":3}]},{"name":"Iceburg - Lettuce, 0.5 cup 72g","nutrients":[{"Calories":5}]},{"name":"Iceburg - Lettuce, 0.5 cup 72g","nutrients":[{"Calories":5}]},{"name":"Litehouse - Homestyle Ranch Dressing, 1 Tbsp.","nutrients":[{"Calories":60}]},{"name":"Litehouse - Homestyle Ranch Dressing, 1 Tbsp.","nutrients":[{"Calories":60}]},{"name":"T - Tomato Slice, 34 g 3 wheels","nutrients":[{"Calories":5}]},{"name":"T - Tomato Slice, 34 g 3 wheels","nutrients":[{"Calories":5}]}]}],"summary":{"total":[{"Calories":1129}],"goal":[{"Calories":1713}]}},{"id":9202,"date":"2015-02-25","meals":[{"name":"snack","dishes":[{"name":"Bear Naked - Nutty Double Chocolate Layered Granola Bar, 1 Bar","nutrients":[{"Calories":190}]},{"name":"Bear Naked - Nutty Double Chocolate Layered Granola Bar, 1 Bar","nutrients":[{"Calories":190}]}]},{"name":"lunch","dishes":[{"name":"Sara Lee - Oven Roasted Turkey Deli Meat, 3 oz","nutrients":[{"Calories":90}]},{"name":"Sara Lee - Oven Roasted Turkey Deli Meat, 3 oz","nutrients":[{"Calories":90}]},{"name":"Toufayan - Pita Bread Whole Wheat, 1 loaf 56 g","nutrients":[{"Calories":150}]},{"name":"Toufayan - Pita Bread Whole Wheat, 1 loaf 56 g","nutrients":[{"Calories":150}]},{"name":"Aldi Burman's - Yellow Mustard, 2 tsp.","nutrients":[{"Calories":0}]},{"name":"Aldi Burman's - Yellow Mustard, 2 tsp.","nutrients":[{"Calories":0}]},{"name":"Fresh Attitude - Baby Spinach, 0.25 g 2 cups","nutrients":[{"Calories":0}]},{"name":"Fresh Attitude - Baby Spinach, 0.25 g 2 cups","nutrients":[{"Calories":0}]},{"name":"Generic - Tomato, Red, Sliced, 1 slice","nutrients":[{"Calories":4}]},{"name":"Generic - Tomato, Red, Sliced, 1 slice","nutrients":[{"Calories":4}]}]},{"name":"snack","dishes":[{"name":"Halo - Mandarin Oranges, 1 Oranges","nutrients":[{"Calories":40}]},{"name":"Halo - Mandarin Oranges, 1 Oranges","nutrients":[{"Calories":40}]},{"name":"Bananas - Raw, 1 medium 7 to 7-7/8 long","nutrients":[{"Calories":105}]},{"name":"Bananas - Raw, 1 medium 7 to 7-7/8 long","nutrients":[{"Calories":105}]}]},{"name":"dinner","dishes":[{"name":"Great Value - Bonless Skinless Chicken Breasts Fillets, 5 oz 112g","nutrients":[{"Calories":138}]},{"name":"Great Value - Bonless Skinless Chicken Breasts Fillets, 5 oz 112g","nutrients":[{"Calories":138}]},{"name":"Homemade - Sauteed Peppers, Onion and Mushrooms, 5/8 cup","nutrients":[{"Calories":75}]},{"name":"Homemade - Sauteed Peppers, Onion and Mushrooms, 5/8 cup","nutrients":[{"Calories":75}]},{"name":"Homemade From Scratch - Flour Tortilla, 3 tortilla 37g","nutrients":[{"Calories":360}]},{"name":"Homemade From Scratch - Flour Tortilla, 3 tortilla 37g","nutrients":[{"Calories":360}]},{"name":"Soda, Sprite - Soda, Sprite, 12 oz","nutrients":[{"Calories":140}]},{"name":"Soda, Sprite - Soda, Sprite, 12 oz","nutrients":[{"Calories":140}]}]}],"summary":{"total":[{"Calories":1292}],"goal":[{"Calories":1681}]}},{"id":9202,"date":"2015-03-06","meals":[{"name":"breakfast","dishes":[{"name":"Bear Naked - Nutty Double Chocolate Layered Granola Bar, 1 Bar","nutrients":[{"Calories":190}]},{"name":"Bear Naked - Nutty Double Chocolate Layered Granola Bar, 1 Bar","nutrients":[{"Calories":190}]}]},{"name":"snack","dishes":[{"name":"Bear Naked - Fruit and Nutty Layered Granola Bar, 1 bar","nutrients":[{"Calories":170}]},{"name":"Bear Naked - Fruit and Nutty Layered Granola Bar, 1 bar","nutrients":[{"Calories":170}]}]}],"summary":{"total":[{"Calories":360}],"goal":[{"Calories":1430}]}},{"id":9202,"date":"2015-03-11","meals":[{"name":"lunch","dishes":[{"name":"Dr. Pepper - Heritage Can, 12 fl. oz. can","nutrients":[{"Calories":150}]},{"name":"Dr. Pepper - Heritage Can, 12 fl. oz. can","nutrients":[{"Calories":150}]}]},{"name":"dinner","dishes":[{"name":"Fresh Attitude - Baby Spinich, 0.5 cups","nutrients":[{"Calories":3}]},{"name":"Fresh Attitude - Baby Spinich, 0.5 cups","nutrients":[{"Calories":3}]},{"name":"Sara Lee - Oven Roasted Turkey Deli Meat, 5 oz","nutrients":[{"Calories":150}]},{"name":"Sara Lee - Oven Roasted Turkey Deli Meat, 5 oz","nutrients":[{"Calories":150}]},{"name":"Generic - Tomato, Red, Sliced, 1 slice","nutrients":[{"Calories":4}]},{"name":"Generic - Tomato, Red, Sliced, 1 slice","nutrients":[{"Calories":4}]},{"name":"Burman's - Real Honey Honey Mustard, 2 tsp 5g","nutrients":[{"Calories":20}]},{"name":"Burman's - Real Honey Honey Mustard, 2 tsp 5g","nutrients":[{"Calories":20}]},{"name":"Alpine Lace - 25% Reduced Fat Swiss Cheese, 1 Slice","nutrients":[{"Calories":70}]},{"name":"Alpine Lace - 25% Reduced Fat Swiss Cheese, 1 Slice","nutrients":[{"Calories":70}]},{"name":"Loven Fresh Honey Wheat Aldi - Honey Wheat Bread, 2 slices","nutrients":[{"Calories":120}]},{"name":"Loven Fresh Honey Wheat Aldi - Honey Wheat Bread, 2 slices","nutrients":[{"Calories":120}]},{"name":"Guittard - Semi Sweet Chocolate Chips, 30 pieces 15g","nutrients":[{"Calories":70}]},{"name":"Guittard - Semi Sweet Chocolate Chips, 30 pieces 15g","nutrients":[{"Calories":70}]},{"name":"Potato - Salad - Loaded , 0.25 Cup","nutrients":[{"Calories":53}]},{"name":"Potato - Salad - Loaded , 0.25 Cup","nutrients":[{"Calories":53}]}]}],"summary":{"total":[{"Calories":640}],"goal":[{"Calories":1430}]}}]